{
    "questions": [
        {
            "question": "一个人从 30 层楼跳下来，为什么没有摔死？",
            "answer": "从 1 楼跳下来",
            "hint": "题目没说从哪里跳下来"
        },
        {
            "question": "什么东西越洗越脏？",
            "answer": "水",
            "hint": "想想洗东西用的是什么"
        },
        {
            "question": "什么东西装玻璃，爱把鱼虾关？",
            "answer": "鱼缸",
            "hint": "一个养鱼的容器"
        },
        {
            "question": "什么东西没手没脚会走，没眼没嘴会说话？",
            "answer": "钟表",
            "hint": "能走能说的物品"
        },
        {
            "question": "什么东西越吃越感到饿？",
            "answer": "筷子",
            "hint": "吃饭用的工具"
        },
        {
            "question": "什么东西在刀刃上跳舞？",
            "answer": "剃须刀片上的胡须",
            "hint": "和刮胡子有关"
        },
        {
            "question": "什么东西走着走着就没有了？",
            "answer": "路",
            "hint": "走完就到了"
        },
        {
            "question": "什么东西人们最爱往里钻？",
            "answer": "钱眼",
            "hint": "和金钱有关"
        },
        {
            "question": "什么东西越来越小，越来越贵重？",
            "answer": "钻石",
            "hint": "一种珍贵的宝石"
        },
        {
            "question": "什么东西只有头和身子，没有手和脚？",
            "answer": "筷子",
            "hint": "吃饭用的工具"
        },
        {
            "question": "什么东西只有两个字，却被人念成三个字？",
            "answer": "谢谢",
            "hint": "一个礼貌用语"
        },
        {
            "question": "什么东西只能在冬天吃？",
            "answer": "冰棍",
            "hint": "夏天就化了"
        },
        {
            "question": "什么东西只有黑人才能吃？",
            "answer": "黑人牙膏",
            "hint": "一个品牌名称"
        },
        {
            "question": "什么东西只有男人才能吃？",
            "answer": "男人烟",
            "hint": "一个品牌名称"
        },
        {
            "question": "什么东西只有女人才能吃？",
            "answer": "女人香烟",
            "hint": "一个品牌名称"
        },
        {
            "question": "什么东西只有小孩才能吃？",
            "answer": "奶粉",
            "hint": "婴儿食品"
        },
        {
            "question": "什么东西只有老人才能吃？",
            "answer": "老人参",
            "hint": "一种补品"
        },
        {
            "question": "什么东西越热越爱出来？",
            "answer": "汗",
            "hint": "人体分泌物"
        },
        {
            "question": "什么东西越冷越爱出来？",
            "answer": "鼻涕",
            "hint": "人体分泌物"
        },
        {
            "question": "什么东西越长越短？",
            "answer": "蜡烛",
            "hint": "会燃烧的物品"
        },
        {
            "question": "什么东西越短越长？",
            "answer": "头发",
            "hint": "剪短了会重新长"
        },
        {
            "question": "什么东西越走越少？",
            "answer": "寿命",
            "hint": "时间相关"
        },
        {
            "question": "什么东西越少越好？",
            "answer": "灾难",
            "hint": "不好的事情"
        },
        {
            "question": "什么东西越多越好？",
            "answer": "福气",
            "hint": "好的事情"
        },
        {
            "question": "什么东西越黑越亮？",
            "answer": "眼睛",
            "hint": "人体器官"
        },
        {
            "question": "什么东西越白越亮？",
            "answer": "牙齿",
            "hint": "人体器官"
        },
        {
            "question": "什么东西越亮越黑？",
            "answer": "太阳镜",
            "hint": "一种眼镜"
        },
        {
            "question": "什么东西越黑越红？",
            "answer": "木炭",
            "hint": "燃烧的物品"
        },
        {
            "question": "什么东西越红越黑？",
            "answer": "夕阳",
            "hint": "自然现象"
        },
        {
            "question": "什么东西越老越值钱？",
            "answer": "古董",
            "hint": "收藏品"
        },
        {
            "question": "什么东西越值钱越便宜？",
            "answer": "邮票",
            "hint": "集邮用品"
        },
        {
            "question": "什么东西越便宜越贵？",
            "answer": "打折商品",
            "hint": "商场促销"
        },
        {
            "question": "什么东西越贵越便宜？",
            "answer": "废品",
            "hint": "可回收物品"
        },
        {
            "question": "什么东西越高越低？",
            "answer": "温度",
            "hint": "气象相关"
        },
        {
            "question": "什么东西越低越高？",
            "answer": "气压",
            "hint": "气象相关"
        },
        {
            "question": "什么东西越深越浅？",
            "answer": "睡眠",
            "hint": "人的生理现象"
        },
        {
            "question": "什么东西越浅越深？",
            "answer": "感情",
            "hint": "人的情感"
        },
        {
            "question": "什么东西越轻越重？",
            "answer": "心事",
            "hint": "心理负担"
        },
        {
            "question": "什么东西越重越轻？",
            "answer": "钱包",
            "hint": "装钱的物品"
        },
        {
            "question": "什么东西越大越小？",
            "answer": "年龄",
            "hint": "时间相关"
        },
        {
            "question": "什么东西越小越大？",
            "answer": "问题",
            "hint": "麻烦事"
        },


        {
            "question": "为什么新买的袜子有两个洞?",
            "answer": "两个洞才能穿进去两只脚",
            "hint": "想想袜子的用途"
        },
        {
            "question": "有两个人掉到陷阱里了，死的人叫死人，活人叫什么？",
            "answer": "叫救命",
            "hint": "想想活人会做什么"
        },
        {
            "question": "做鸡蛋面的老板是谁？",
            "answer": "西红柿",
            "hint": "西红柿炒鸡蛋"
        },
        {
            "question": "最不听话的人是谁?",
            "answer": "聋子",
            "hint": "听不见的人"
        },
        {
            "question": "一只乌龟掉进山崖里（猜一花名）？",
            "answer": "玫瑰",
            "hint": "没龟的谐音"
        },
        {
            "question": "又一只乌龟掉进山崖（猜一花名）?",
            "answer": "野玫瑰",
            "hint": "也没龟的谐音"
        },
        {
            "question": "小白加小白等于什么？",
            "answer": "小白兔",
            "hint": "two的谐音"
        },
        {
            "question": "什么蛋中看不中吃？",
            "answer": "脸蛋",
            "hint": "人体部位"
        },
        {
            "question": "哪种水果视力特别差？",
            "answer": "芒果",
            "hint": "盲的谐音"
        },
        {
            "question": "麒麟飞到北极会变成什么？",
            "answer": "冰淇淋",
            "hint": "温度变化"
        },
        {
            "question": "离婚的主要起因是什么？",
            "answer": "结婚",
            "hint": "没有结婚就不会离婚"
        },
        {
            "question": "别人请你吃什么需要你自己花钱？",
            "answer": "吃官司",
            "hint": "法律相关"
        },
        {
            "question": "大象的左耳朵像什么？",
            "answer": "右耳朵",
            "hint": "对称器官"
        },
        {
            "question": "什么东西力气再大也不愿意抗？",
            "answer": "罪名",
            "hint": "法律相关"
        },
        {
            "question": "什么事你明明没做却要受罚？",
            "answer": "作业",
            "hint": "学生最怕的事"
        },
        {
            "question": "什么东西只能加不能减？",
            "answer": "年龄",
            "hint": "时间相关"
        },
        {
            "question": "什么布不能做衣服？",
            "answer": "瀑布",
            "hint": "自然景观"
        },
        {
            "question": "武松到底犯了什么罪被抓起来？",
            "answer": "打死老虎",
            "hint": "水浒传故事"
        },
        {
            "question": "你知道现代科学家从哪里出生的吗？",
            "answer": "妈妈的肚子里",
            "hint": "所有人都一样"
        },
        {
            "question": "9月28是孔子诞辰,那么10月28日是什么日子？",
            "answer": "孔子满月",
            "hint": "婴儿出生后的日子"
        },

        {
            "question": "猪圈里的猪跑出来怎么办？",
            "answer": "王力宏",
            "hint": "往里哄的谐音"
        },
        {
            "question": "一头牛面北朝南，然后转了一圈，牛尾巴朝哪里？",
            "answer": "朝地下",
            "hint": "想想尾巴的位置"
        },
        {
            "question": "这两块冰下有鲤鱼（四字成语）?",
            "answer": "彬彬有礼",
            "hint": "冰冰有鲤的谐音"
        },
        {
            "question": "要形容一个丑女长得漂亮，说什么话她最高兴？",
            "answer": "谎话",
            "hint": "不诚实的话"
        },
        {
            "question": "耶稣是哪国人？",
            "answer": "天国",
            "hint": "宗教相关"
        },
        {
            "question": "茉莉花、太阳花、玫瑰花哪一朵最漂亮？",
            "answer": "茉莉花",
            "hint": "好一朵美丽的茉莉花"
        },
        {
            "question": "有人说女人像一本书，那么胖女人像什么书?",
            "answer": "合订本",
            "hint": "书的种类"
        },
        {
            "question": "什么船不用水就可以航行?",
            "answer": "宇宙飞船",
            "hint": "太空交通工具"
        },
        {
            "question": "爸爸什么时候像个孩子？",
            "answer": "跟爷爷一起的时候",
            "hint": "辈分关系"
        },
        {
            "question": "时钟敲了十三下该怎么做？",
            "answer": "修理它",
            "hint": "正常时钟最多敲12下"
        },
        {
            "question": "怎么让猪不要飞走？",
            "answer": "插上翅膀",
            "hint": "插翅难飞"
        },
        {
            "question": "世界上谁的肚子最大？",
            "answer": "宰相",
            "hint": "宰相肚里能撑船"
        },
        {
            "question": "什么动物的屁股不能碰？",
            "answer": "老虎",
            "hint": "老虎的屁股摸不得"
        },
        {
            "question": "什么鬼走路东倒西歪？",
            "answer": "酒鬼",
            "hint": "喝醉的人"
        },
        {
            "question": "猪蹄、猪耳朵，猪肉都很好吃，那除了猪除了吃还有什么用处？",
            "answer": "还可以用来骂人",
            "hint": "贬义词"
        },
        {
            "question": "阿拉丁爸爸的哥哥是谁？",
            "answer": "阿拉伯",
            "hint": "名字的谐音"
        },
        {
            "question": "黄豆年轻的时候叫什么？",
            "answer": "青春痘",
            "hint": "脸上会长的东西"
        },
        {
            "question": "在所有植物中，什么植物最老实？",
            "answer": "芭蕉",
            "hint": "老实巴交"
        },
        {
            "question": "什么时候别人敲的你门不让进？",
            "answer": "厕所",
            "hint": "私密场所"
        },
        {
            "question": "失败是成功之母，那成功为失败的什么?",
            "answer": "反义词",
            "hint": "词语关系"
        },

        {
            "question": "日月潭中间是什么？",
            "answer": "月",
            "hint": "看看这三个字中间的字"
        },
        {
            "question": "拿什么东西不用手？",
            "answer": "拿主意",
            "hint": "用脑子的事"
        },
        {
            "question": "时钟什么时候不会走？",
            "answer": "时钟本来就不会走",
            "hint": "想想走路需要什么"
        },
        {
            "question": "想从北京去巴黎需要多少钱？",
            "answer": "想不需要钱",
            "hint": "注意题目第一个字"
        },
        {
            "question": "世界最结实的琴是什么琴？",
            "answer": "钢琴",
            "hint": "乐器材质"
        },
        {
            "question": "小王走路从来脚不沾地，这是为什么呢？",
            "answer": "穿着鞋子",
            "hint": "想想脚和地之间有什么"
        },
        {
            "question": "人们最不喜欢的是哪种草？",
            "answer": "墙头草",
            "hint": "一个贬义词"
        },
        {
            "question": "为什么关羽比张飞死得早？",
            "answer": "红颜薄命",
            "hint": "红面关公"
        },
        {
            "question": "把火熄灭的最快方法？",
            "answer": "火字上面加一横",
            "hint": "汉字的写法"
        },
        {
            "question": "哭和笑有什么共同之处？",
            "answer": "笔画数相同",
            "hint": "看看这两个字的结构"
        },
        {
            "question": "增长智力的有效方法是什么？",
            "answer": "吃一堑长一智",
            "hint": "一个成语"
        },
        {
            "question": "聪明人比一般人多了个什么？",
            "answer": "心眼",
            "hint": "形容精明的词"
        },
        {
            "question": "打狗看主人，打虎看什么？",
            "answer": "看你有没有胆子",
            "hint": "考验勇气"
        },
        {
            "question": "家里又脏又乱，怎么才能在最短时间弄干净？",
            "answer": "闭上眼",
            "hint": "眼不见为净"
        },
        {
            "question": "大熊猫一生中最大的遗憾是什么？",
            "answer": "没有彩色照片",
            "hint": "想想熊猫的颜色"
        },
        {
            "question": "乌龟为什么会突然一个头两个大？",
            "answer": "因为乌龟正在想这个问题",
            "hint": "想事情的表现"
        },
        {
            "question": "一颗心值多少钱?",
            "answer": "1亿",
            "hint": "一心一意"
        },
        {
            "question": "怎样使麻雀安静下来？",
            "answer": "压它一下",
            "hint": "鸦雀无声"
        },
        {
            "question": "小明天天吃口香糖，可别人还说他口臭，为什么？",
            "answer": "他天天说脏话",
            "hint": "不是真的口臭"
        },
        {
            "question": "为什么有钱人家的狗比较安静，不会朝其他的狗乱叫？",
            "answer": "苟富贵，勿相忘",
            "hint": "一句古语"
        },

        {
            "question": "什么马不能骑？",
            "answer": "驸马",
            "hint": "古代官职"
        },
        {
            "question": "什么东西明明是你的别人用得最多？",
            "answer": "你的名字",
            "hint": "身份标识"
        },
        {
            "question": "牙医靠什么吃饭？",
            "answer": "靠嘴巴",
            "hint": "身体部位"
        },
        {
            "question": "米的妈妈是谁？",
            "answer": "花",
            "hint": "花生米"
        },
        {
            "question": "花生米的爸爸是谁？",
            "answer": "蝶",
            "hint": "蝶恋花"
        },
        {
            "question": "米的外公是谁？",
            "answer": "爆米花",
            "hint": "爆过米也爆过花"
        },
        {
            "question": "米的外婆是谁？",
            "answer": "妙笔",
            "hint": "妙笔生花"
        },
        {
            "question": "米的舅舅是谁？",
            "answer": "辉",
            "hint": "妙笔生辉"
        },
        {
            "question": "什么人是不用电的？",
            "answer": "缅甸人",
            "hint": "免电人的谐音"
        },
        {
            "question": "盲人是怎样吃橘子的？",
            "answer": "瞎掰",
            "hint": "双关语"
        },
        {
            "question": "什么动物可以贴在墙上？",
            "answer": "海豹",
            "hint": "海报的谐音"
        },
        {
            "question": "为什么大部分佛教徒都住在北半球？",
            "answer": "南无阿弥陀佛",
            "hint": "佛教用语"
        },
        {
            "question": "象皮、老虎皮、狮子皮哪一个比较差？",
            "answer": "象皮",
            "hint": "象皮差的谐音"
        },
        {
            "question": "有位妈妈生了连体婴，姐姐叫玛丽，那么妹妹叫做什么?",
            "answer": "梦露",
            "hint": "玛利莲梦露"
        },
        {
            "question": "小狗和小兔去老师那里背书，老师会让谁先背?",
            "answer": "小狗",
            "hint": "旺旺仙贝"
        },
        {
            "question": "哪一首歌的第一句就出现了3个人?",
            "answer": "我不是黄蓉",
            "hint": "我，布什，黄蓉"
        },
        {
            "question": "用椰子和西瓜打头哪一个比较疼?",
            "answer": "头比较疼",
            "hint": "注意问题的主语"
        },
        {
            "question": "如果动物园失火了，最先逃出来的哪一种动物?",
            "answer": "人",
            "hint": "最聪明的动物"
        },
        {
            "question": "人的长寿秘诀是什么？",
            "answer": "保持呼吸，不要断气",
            "hint": "最基本的生命特征"
        },
        {
            "question": "你知道为什么在人群中一眼就能看到你吗？",
            "answer": "慧眼识珠",
            "hint": "珠和猪的谐音"
        }
    ]
}